qamodel/__init__.py
qamodel/data_loader.py
qamodel/dataset.py
qamodel/model.py
qamodel/tokenizer.py
qamodel/train.py
qamodel/utils.py
qamodel-1.0.4.dist-info/LICENSE
qamodel-1.0.4.dist-info/METADATA
qamodel-1.0.4.dist-info/WHEEL
qamodel-1.0.4.dist-info/top_level.txt
qamodel-1.0.4.dist-info/RECORD
